{
  "main": {
    "id": "c7612a5a286e04cf",
    "type": "split",
    "children": [
      {
        "id": "f3342b7a83023535",
        "type": "tabs",
        "children": [
          {
            "id": "afb61862661e343c",
            "type": "leaf",
            "state": {
              "type": "markdown",
              "state": {
                "file": "Deficit Myth.md",
                "mode": "source",
                "source": false
              }
            }
          },
          {
            "id": "b89a255e62fd7404",
            "type": "leaf",
            "state": {
              "type": "markdown",
              "state": {
                "file": "Untitled 1.md",
                "mode": "source",
                "source": false
              }
            }
          },
          {
            "id": "aab5959f55d107ad",
            "type": "leaf",
            "state": {
              "type": "release-notes",
              "state": {
                "currentVersion": "1.4.16"
              }
            }
          }
        ]
      }
    ],
    "direction": "vertical"
  },
  "left": {
    "id": "6050d4eb4e7cfae3",
    "type": "split",
    "children": [
      {
        "id": "22dcea72ac9c3f4a",
        "type": "tabs",
        "children": [
          {
            "id": "f2b41864c0e287d2",
            "type": "leaf",
            "state": {
              "type": "file-explorer",
              "state": {
                "sortOrder": "alphabetical"
              }
            }
          },
          {
            "id": "fff71859529a0bd0",
            "type": "leaf",
            "state": {
              "type": "search",
              "state": {
                "query": "",
                "matchingCase": false,
                "explainSearch": false,
                "collapseAll": false,
                "extraContext": false,
                "sortOrder": "alphabetical"
              }
            }
          },
          {
            "id": "26249233a26e7fce",
            "type": "leaf",
            "state": {
              "type": "bookmarks",
              "state": {}
            }
          }
        ]
      }
    ],
    "direction": "horizontal",
    "width": 318.5
  },
  "right": {
    "id": "97f09a1033a8491f",
    "type": "split",
    "children": [
      {
        "id": "56d0feea9e901505",
        "type": "tabs",
        "children": [
          {
            "id": "69e719f3413ed104",
            "type": "leaf",
            "state": {
              "type": "backlink",
              "state": {
                "file": "Deficit Myth.md",
                "collapseAll": false,
                "extraContext": false,
                "sortOrder": "alphabetical",
                "showSearch": false,
                "searchQuery": "",
                "backlinkCollapsed": false,
                "unlinkedCollapsed": true
              }
            }
          },
          {
            "id": "2433271c0d4d30f3",
            "type": "leaf",
            "state": {
              "type": "all-properties",
              "state": {
                "sortOrder": "frequency"
              }
            }
          }
        ]
      }
    ],
    "direction": "horizontal",
    "width": 300,
    "collapsed": true
  },
  "left-ribbon": {
    "hiddenItems": {
      "switcher:Open quick switcher": false,
      "graph:Open graph view": false,
      "canvas:Create new canvas": false,
      "command-palette:Open command palette": false,
      "markdown-importer:Open format converter": false
    }
  },
  "active": "afb61862661e343c",
  "lastOpenFiles": [
    "Savings vs Investment.md",
    "Deficit Myth.md",
    "WIL/WILT - 11.1.23.md",
    "WIL/WILT - 10.30.23.md",
    "WIL/WILT - Template.md",
    "WIL/WILT - 10.24.23.md",
    "WIL/WILT - 10.23.23.md",
    "Trade Wars are Class Wars.md",
    "Untitled 1.md",
    "Macro vs Idiosyncratic.md",
    "Molecules/Framework.md",
    "Molecules/Credit Buckets.md",
    "Molecules/Edge.md",
    "Long, Slow Death of Global Devlopment.md",
    "Molecules/Systems Examples.md",
    "WIL/WILT - 10.19.23.md",
    "Molecules/Net Assessment - China.md",
    "Outlines/To Read - Outline.md",
    "China - Outline.md",
    "WIL/WILT - 10.17.23.md",
    "WIL/WILT - 10.12.23.md",
    "Molecules/GDP.md",
    "Volatility Machine.md",
    "Bernanke on Savings Glut.md",
    "WIL/WILW - 9.29.23.md",
    "Dirty Hands.md"
  ]
}